{
  "version": "5.10.1",
  "flags": {},
  "shapes": [
    {
      "label": "tomato",
      "points": [
        [
          2206,
          793
        ],
        [
          2193,
          787
        ],
        [
          2184,
          785
        ],
        [
          2177,
          785
        ],
        [
          2167,
          788
        ],
        [
          2147,
          807
        ],
        [
          2143,
          814
        ],
        [
          2130,
          828
        ],
        [
          2126,
          835
        ],
        [
          2112,
          838
        ],
        [
          2103,
          843
        ],
        [
          2102,
          853
        ],
        [
          2107,
          870
        ],
        [
          2112,
          882
        ],
        [
          2121,
          888
        ],
        [
          2127,
          890
        ],
        [
          2134,
          897
        ],
        [
          2143,
          900
        ],
        [
          2164,
          899
        ],
        [
          2181,
          893
        ],
        [
          2190,
          892
        ],
        [
          2207,
          885
        ],
        [
          2215,
          877
        ],
        [
          2221,
          864
        ],
        [
          2223,
          848
        ],
        [
          2224,
          847
        ],
        [
          2224,
          826
        ],
        [
          2219,
          806
        ]
      ],
      "group_id": null,
      "description": "",
      "shape_type": "polygon",
      "flags": {}
    },
    {
      "label": "tomato",
      "points": [
        [
          2061,
          1042
        ],
        [
          2033,
          1043
        ],
        [
          2012,
          1052
        ],
        [
          2006,
          1058
        ],
        [
          1997,
          1079
        ],
        [
          1992,
          1102
        ],
        [
          1978,
          1128
        ],
        [
          1974,
          1150
        ],
        [
          1970,
          1160
        ],
        [
          1969,
          1178
        ],
        [
          1977,
          1203
        ],
        [
          2000,
          1227
        ],
        [
          2019,
          1235
        ],
        [
          2047,
          1237
        ],
        [
          2056,
          1232
        ],
        [
          2073,
          1227
        ],
        [
          2095,
          1211
        ],
        [
          2103,
          1197
        ],
        [
          2105,
          1188
        ],
        [
          2111,
          1175
        ],
        [
          2112,
          1166
        ],
        [
          2119,
          1152
        ],
        [
          2124,
          1135
        ],
        [
          2125,
          1108
        ],
        [
          2118,
          1084
        ],
        [
          2100,
          1064
        ],
        [
          2087,
          1054
        ]
      ],
      "group_id": null,
      "description": "",
      "shape_type": "polygon",
      "flags": {}
    },
    {
      "label": "tomato",
      "points": [
        [
          1899,
          1264
        ],
        [
          1896,
          1270
        ],
        [
          1899,
          1274
        ],
        [
          1907,
          1278
        ],
        [
          1920,
          1281
        ],
        [
          1931,
          1293
        ],
        [
          1929,
          1308
        ],
        [
          1924,
          1321
        ],
        [
          1911,
          1337
        ],
        [
          1901,
          1353
        ],
        [
          1931,
          1373
        ],
        [
          1962,
          1382
        ],
        [
          1966,
          1385
        ],
        [
          1993,
          1385
        ],
        [
          2011,
          1382
        ],
        [
          2023,
          1378
        ],
        [
          2054,
          1362
        ],
        [
          2069,
          1338
        ],
        [
          2071,
          1328
        ],
        [
          2071,
          1308
        ],
        [
          2073,
          1303
        ],
        [
          2073,
          1291
        ],
        [
          2070,
          1279
        ],
        [
          2063,
          1264
        ],
        [
          2050,
          1252
        ],
        [
          2039,
          1245
        ],
        [
          2019,
          1241
        ],
        [
          1998,
          1241
        ],
        [
          1968,
          1238
        ],
        [
          1946,
          1240
        ],
        [
          1920,
          1246
        ],
        [
          1909,
          1253
        ]
      ],
      "group_id": null,
      "description": "",
      "shape_type": "polygon",
      "flags": {}
    },
    {
      "label": "stem",
      "points": [
        [
          984,
          655
        ],
        [
          962,
          648
        ],
        [
          959,
          648
        ],
        [
          958,
          647
        ],
        [
          957,
          647
        ],
        [
          955,
          645
        ],
        [
          955,
          644
        ],
        [
          954,
          643
        ],
        [
          954,
          642
        ],
        [
          952,
          640
        ],
        [
          949,
          640
        ],
        [
          948,
          639
        ],
        [
          945,
          639
        ],
        [
          944,
          638
        ],
        [
          941,
          638
        ],
        [
          940,
          637
        ],
        [
          932,
          637
        ],
        [
          931,
          636
        ],
        [
          929,
          636
        ],
        [
          927,
          634
        ],
        [
          926,
          634
        ],
        [
          926,
          635
        ],
        [
          925,
          636
        ],
        [
          925,
          637
        ],
        [
          922,
          640
        ],
        [
          921,
          640
        ],
        [
          921,
          641
        ],
        [
          928,
          641
        ],
        [
          929,
          642
        ],
        [
          936,
          642
        ],
        [
          937,
          643
        ],
        [
          947,
          643
        ],
        [
          948,
          644
        ],
        [
          950,
          644
        ],
        [
          951,
          645
        ],
        [
          951,
          646
        ],
        [
          952,
          647
        ],
        [
          952,
          648
        ],
        [
          962,
          648
        ],
        [
          984,
          655
        ],
        [
          1103,
          704
        ],
        [
          1210,
          766
        ],
        [
          1267,
          810
        ],
        [
          1322,
          865
        ],
        [
          1383,
          984
        ],
        [
          1378,
          993
        ],
        [
          1287,
          976
        ],
        [
          1161,
          915
        ],
        [
          1137,
          894
        ],
        [
          1092,
          884
        ],
        [
          1061,
          855
        ],
        [
          1026,
          849
        ],
        [
          1009,
          836
        ],
        [
          1008,
          835
        ],
        [
          1008,
          834
        ],
        [
          1007,
          833
        ],
        [
          1007,
          831
        ],
        [
          1006,
          830
        ],
        [
          1006,
          829
        ],
        [
          999,
          829
        ],
        [
          992,
          828
        ],
        [
          991,
          827
        ],
        [
          990,
          827
        ],
        [
          989,
          826
        ],
        [
          987,
          826
        ],
        [
          986,
          825
        ],
        [
          982,
          825
        ],
        [
          981,
          824
        ],
        [
          977,
          824
        ],
        [
          976,
          825
        ],
        [
          974,
          823
        ],
        [
          974,
          820
        ],
        [
          973,
          820
        ],
        [
          972,
          819
        ],
        [
          970,
          819
        ],
        [
          969,
          818
        ],
        [
          965,
          818
        ],
        [
          963,
          820
        ],
        [
          963,
          821
        ],
        [
          964,
          821
        ],
        [
          966,
          823
        ],
        [
          974,
          823
        ],
        [
          976,
          825
        ],
        [
          976,
          828
        ],
        [
          977,
          828
        ],
        [
          978,
          829
        ],
        [
          990,
          829
        ],
        [
          991,
          828
        ],
        [
          992,
          828
        ],
        [
          999,
          829
        ],
        [
          1000,
          830
        ],
        [
          1000,
          831
        ],
        [
          1001,
          832
        ],
        [
          1001,
          835
        ],
        [
          1002,
          836
        ],
        [
          1003,
          836
        ],
        [
          1004,
          837
        ],
        [
          1005,
          837
        ],
        [
          1006,
          838
        ],
        [
          1007,
          838
        ],
        [
          1009,
          836
        ],
        [
          1026,
          849
        ],
        [
          1032,
          859
        ],
        [
          1057,
          869
        ],
        [
          1073,
          887
        ],
        [
          1126,
          903
        ],
        [
          1275,
          986
        ],
        [
          1391,
          1013
        ],
        [
          1425,
          1050
        ],
        [
          1481,
          1138
        ],
        [
          1555,
          1211
        ],
        [
          1553,
          1226
        ],
        [
          1588,
          1252
        ],
        [
          1611,
          1256
        ],
        [
          1646,
          1293
        ],
        [
          1646,
          1294
        ],
        [
          1650,
          1295
        ],
        [
          1657,
          1303
        ],
        [
          1663,
          1305
        ],
        [
          1673,
          1317
        ],
        [
          1678,
          1318
        ],
        [
          1686,
          1323
        ],
        [
          1690,
          1323
        ],
        [
          1703,
          1327
        ],
        [
          1709,
          1331
        ],
        [
          1699,
          1381
        ],
        [
          1698,
          1382
        ],
        [
          1691,
          1382
        ],
        [
          1690,
          1383
        ],
        [
          1685,
          1383
        ],
        [
          1684,
          1382
        ],
        [
          1682,
          1382
        ],
        [
          1681,
          1381
        ],
        [
          1676,
          1381
        ],
        [
          1675,
          1380
        ],
        [
          1673,
          1380
        ],
        [
          1672,
          1381
        ],
        [
          1671,
          1381
        ],
        [
          1669,
          1383
        ],
        [
          1669,
          1384
        ],
        [
          1670,
          1385
        ],
        [
          1670,
          1387
        ],
        [
          1671,
          1388
        ],
        [
          1671,
          1391
        ],
        [
          1673,
          1393
        ],
        [
          1673,
          1394
        ],
        [
          1675,
          1394
        ],
        [
          1676,
          1395
        ],
        [
          1677,
          1395
        ],
        [
          1685,
          1403
        ],
        [
          1686,
          1406
        ],
        [
          1688,
          1406
        ],
        [
          1689,
          1407
        ],
        [
          1692,
          1408
        ],
        [
          1699,
          1415
        ],
        [
          1701,
          1415
        ],
        [
          1702,
          1416
        ],
        [
          1705,
          1416
        ],
        [
          1706,
          1417
        ],
        [
          1707,
          1417
        ],
        [
          1711,
          1421
        ],
        [
          1712,
          1421
        ],
        [
          1713,
          1422
        ],
        [
          1716,
          1422
        ],
        [
          1717,
          1423
        ],
        [
          1718,
          1423
        ],
        [
          1720,
          1425
        ],
        [
          1721,
          1428
        ],
        [
          1722,
          1429
        ],
        [
          1723,
          1429
        ],
        [
          1726,
          1432
        ],
        [
          1727,
          1432
        ],
        [
          1728,
          1431
        ],
        [
          1730,
          1431
        ],
        [
          1732,
          1429
        ],
        [
          1731,
          1426
        ],
        [
          1727,
          1421
        ],
        [
          1727,
          1419
        ],
        [
          1726,
          1418
        ],
        [
          1726,
          1417
        ],
        [
          1723,
          1414
        ],
        [
          1722,
          1414
        ],
        [
          1721,
          1413
        ],
        [
          1718,
          1413
        ],
        [
          1717,
          1412
        ],
        [
          1714,
          1411
        ],
        [
          1709,
          1406
        ],
        [
          1709,
          1405
        ],
        [
          1706,
          1402
        ],
        [
          1705,
          1399
        ],
        [
          1703,
          1397
        ],
        [
          1702,
          1394
        ],
        [
          1700,
          1392
        ],
        [
          1700,
          1391
        ],
        [
          1699,
          1390
        ],
        [
          1700,
          1389
        ],
        [
          1700,
          1383
        ],
        [
          1699,
          1382
        ],
        [
          1699,
          1381
        ],
        [
          1709,
          1331
        ],
        [
          1728,
          1338
        ],
        [
          1744,
          1339
        ],
        [
          1754,
          1341
        ],
        [
          1769,
          1335
        ],
        [
          1780,
          1333
        ],
        [
          1788,
          1329
        ],
        [
          1794,
          1324
        ],
        [
          1806,
          1323
        ],
        [
          1813,
          1316
        ],
        [
          1906,
          1366
        ],
        [
          1906,
          1367
        ],
        [
          1905,
          1368
        ],
        [
          1905,
          1376
        ],
        [
          1906,
          1377
        ],
        [
          1906,
          1380
        ],
        [
          1907,
          1381
        ],
        [
          1907,
          1387
        ],
        [
          1906,
          1388
        ],
        [
          1906,
          1392
        ],
        [
          1905,
          1393
        ],
        [
          1905,
          1395
        ],
        [
          1904,
          1396
        ],
        [
          1904,
          1398
        ],
        [
          1903,
          1399
        ],
        [
          1903,
          1406
        ],
        [
          1905,
          1409
        ],
        [
          1905,
          1411
        ],
        [
          1906,
          1412
        ],
        [
          1906,
          1414
        ],
        [
          1907,
          1415
        ],
        [
          1907,
          1419
        ],
        [
          1908,
          1420
        ],
        [
          1908,
          1430
        ],
        [
          1909,
          1431
        ],
        [
          1909,
          1436
        ],
        [
          1910,
          1437
        ],
        [
          1910,
          1438
        ],
        [
          1913,
          1440
        ],
        [
          1914,
          1634
        ],
        [
          1912,
          1634
        ],
        [
          1911,
          1635
        ],
        [
          1910,
          1635
        ],
        [
          1909,
          1636
        ],
        [
          1909,
          1637
        ],
        [
          1908,
          1638
        ],
        [
          1908,
          1641
        ],
        [
          1909,
          1642
        ],
        [
          1909,
          1645
        ],
        [
          1910,
          1646
        ],
        [
          1910,
          1647
        ],
        [
          1909,
          1648
        ],
        [
          1909,
          1650
        ],
        [
          1906,
          1653
        ],
        [
          1902,
          1653
        ],
        [
          1903,
          1653
        ],
        [
          1904,
          1654
        ],
        [
          1909,
          1654
        ],
        [
          1910,
          1655
        ],
        [
          1904,
          1679
        ],
        [
          1899,
          1679
        ],
        [
          1899,
          1680
        ],
        [
          1898,
          1681
        ],
        [
          1898,
          1682
        ],
        [
          1897,
          1683
        ],
        [
          1897,
          1696
        ],
        [
          1896,
          1697
        ],
        [
          1896,
          1701
        ],
        [
          1897,
          1702
        ],
        [
          1897,
          1707
        ],
        [
          1898,
          1708
        ],
        [
          1898,
          1709
        ],
        [
          1900,
          1711
        ],
        [
          1900,
          1718
        ],
        [
          1899,
          1719
        ],
        [
          1899,
          1726
        ],
        [
          1900,
          1728
        ],
        [
          1896,
          1732
        ],
        [
          1895,
          1736
        ],
        [
          1891,
          1742
        ],
        [
          1891,
          1746
        ],
        [
          1893,
          1749
        ],
        [
          1893,
          1754
        ],
        [
          1892,
          1755
        ],
        [
          1891,
          1761
        ],
        [
          1890,
          1762
        ],
        [
          1890,
          1769
        ],
        [
          1892,
          1774
        ],
        [
          1893,
          1782
        ],
        [
          1892,
          1783
        ],
        [
          1892,
          1786
        ],
        [
          1891,
          1788
        ],
        [
          1885,
          1794
        ],
        [
          1885,
          1803
        ],
        [
          1890,
          1810
        ],
        [
          1890,
          1822
        ],
        [
          1891,
          1823
        ],
        [
          1891,
          1828
        ],
        [
          1889,
          1830
        ],
        [
          1887,
          1830
        ],
        [
          1886,
          1831
        ],
        [
          1886,
          1836
        ],
        [
          1886,
          1845
        ],
        [
          1885,
          1846
        ],
        [
          1885,
          1847
        ],
        [
          1884,
          1848
        ],
        [
          1884,
          1850
        ],
        [
          1885,
          1851
        ],
        [
          1885,
          1856
        ],
        [
          1884,
          1857
        ],
        [
          1884,
          1858
        ],
        [
          1882,
          1860
        ],
        [
          1882,
          1861
        ],
        [
          1881,
          1862
        ],
        [
          1881,
          1863
        ],
        [
          1880,
          1864
        ],
        [
          1880,
          1869
        ],
        [
          1879,
          1870
        ],
        [
          1879,
          1871
        ],
        [
          1878,
          1872
        ],
        [
          1878,
          1873
        ],
        [
          1876,
          1875
        ],
        [
          1876,
          1876
        ],
        [
          1873,
          1879
        ],
        [
          1873,
          1885
        ],
        [
          1872,
          1886
        ],
        [
          1872,
          1889
        ],
        [
          1871,
          1890
        ],
        [
          1871,
          1891
        ],
        [
          1870,
          1892
        ],
        [
          1870,
          1894
        ],
        [
          1871,
          1895
        ],
        [
          1871,
          1896
        ],
        [
          1872,
          1897
        ],
        [
          1872,
          1898
        ],
        [
          1873,
          1899
        ],
        [
          1860,
          1922
        ],
        [
          1857,
          1923
        ],
        [
          1853,
          1927
        ],
        [
          1853,
          1929
        ],
        [
          1851,
          1933
        ],
        [
          1850,
          1939
        ],
        [
          1851,
          1940
        ],
        [
          1851,
          1954
        ],
        [
          1852,
          1955
        ],
        [
          1853,
          1965
        ],
        [
          1852,
          1966
        ],
        [
          1852,
          1970
        ],
        [
          1851,
          1972
        ],
        [
          1849,
          1974
        ],
        [
          1846,
          1975
        ],
        [
          1846,
          1981
        ],
        [
          1845,
          1982
        ],
        [
          1845,
          1986
        ],
        [
          1843,
          1990
        ],
        [
          1843,
          2000
        ],
        [
          1842,
          2001
        ],
        [
          1842,
          2006
        ],
        [
          1841,
          2007
        ],
        [
          1841,
          2016
        ],
        [
          1843,
          2020
        ],
        [
          1843,
          2027
        ],
        [
          1846,
          2030
        ],
        [
          1837,
          2038
        ],
        [
          1835,
          2038
        ],
        [
          1834,
          2037
        ],
        [
          1833,
          2037
        ],
        [
          1825,
          2044
        ],
        [
          1825,
          2046
        ],
        [
          1823,
          2050
        ],
        [
          1823,
          2052
        ],
        [
          1825,
          2055
        ],
        [
          1825,
          2058
        ],
        [
          1826,
          2059
        ],
        [
          1826,
          2063
        ],
        [
          1827,
          2064
        ],
        [
          1827,
          2076
        ],
        [
          1828,
          2077
        ],
        [
          1828,
          2082
        ],
        [
          1826,
          2085
        ],
        [
          1822,
          2087
        ],
        [
          1820,
          2087
        ],
        [
          1816,
          2101
        ],
        [
          1814,
          2104
        ],
        [
          1814,
          2118
        ],
        [
          1808,
          2125
        ],
        [
          1808,
          2127
        ],
        [
          1806,
          2131
        ],
        [
          1805,
          2139
        ],
        [
          1804,
          2140
        ],
        [
          1804,
          2146
        ],
        [
          1803,
          2147
        ],
        [
          1804,
          2150
        ],
        [
          1807,
          2153
        ],
        [
          1812,
          2153
        ],
        [
          1817,
          2155
        ],
        [
          1820,
          2155
        ],
        [
          1827,
          2148
        ],
        [
          1820,
          2141
        ],
        [
          1819,
          2135
        ],
        [
          1817,
          2135
        ],
        [
          1816,
          2134
        ],
        [
          1818,
          2132
        ],
        [
          1820,
          2132
        ],
        [
          1823,
          2127
        ],
        [
          1823,
          2121
        ],
        [
          1822,
          2120
        ],
        [
          1822,
          2117
        ],
        [
          1823,
          2116
        ],
        [
          1823,
          2113
        ],
        [
          1824,
          2112
        ],
        [
          1824,
          2109
        ],
        [
          1826,
          2104
        ],
        [
          1826,
          2100
        ],
        [
          1829,
          2092
        ],
        [
          1833,
          2089
        ],
        [
          1833,
          2081
        ],
        [
          1836,
          2073
        ],
        [
          1836,
          2069
        ],
        [
          1835,
          2068
        ],
        [
          1835,
          2066
        ],
        [
          1836,
          2065
        ],
        [
          1836,
          2054
        ],
        [
          1837,
          2053
        ],
        [
          1837,
          2048
        ],
        [
          1840,
          2043
        ],
        [
          1839,
          2042
        ],
        [
          1839,
          2040
        ],
        [
          1837,
          2038
        ],
        [
          1846,
          2030
        ],
        [
          1846,
          2024
        ],
        [
          1847,
          2023
        ],
        [
          1847,
          2019
        ],
        [
          1848,
          2018
        ],
        [
          1848,
          2015
        ],
        [
          1850,
          2011
        ],
        [
          1856,
          2006
        ],
        [
          1860,
          2005
        ],
        [
          1862,
          2001
        ],
        [
          1862,
          1988
        ],
        [
          1861,
          1987
        ],
        [
          1861,
          1982
        ],
        [
          1860,
          1981
        ],
        [
          1860,
          1974
        ],
        [
          1861,
          1973
        ],
        [
          1861,
          1969
        ],
        [
          1862,
          1968
        ],
        [
          1862,
          1962
        ],
        [
          1870,
          1946
        ],
        [
          1869,
          1944
        ],
        [
          1869,
          1936
        ],
        [
          1868,
          1935
        ],
        [
          1868,
          1932
        ],
        [
          1866,
          1928
        ],
        [
          1860,
          1922
        ],
        [
          1873,
          1899
        ],
        [
          1873,
          1898
        ],
        [
          1874,
          1897
        ],
        [
          1874,
          1896
        ],
        [
          1875,
          1895
        ],
        [
          1875,
          1894
        ],
        [
          1876,
          1893
        ],
        [
          1876,
          1892
        ],
        [
          1877,
          1891
        ],
        [
          1877,
          1890
        ],
        [
          1878,
          1889
        ],
        [
          1879,
          1889
        ],
        [
          1880,
          1888
        ],
        [
          1882,
          1888
        ],
        [
          1883,
          1887
        ],
        [
          1887,
          1887
        ],
        [
          1889,
          1885
        ],
        [
          1889,
          1883
        ],
        [
          1890,
          1882
        ],
        [
          1890,
          1881
        ],
        [
          1891,
          1880
        ],
        [
          1891,
          1876
        ],
        [
          1890,
          1875
        ],
        [
          1890,
          1872
        ],
        [
          1889,
          1871
        ],
        [
          1889,
          1870
        ],
        [
          1890,
          1869
        ],
        [
          1890,
          1867
        ],
        [
          1891,
          1866
        ],
        [
          1891,
          1861
        ],
        [
          1890,
          1860
        ],
        [
          1890,
          1859
        ],
        [
          1889,
          1858
        ],
        [
          1889,
          1857
        ],
        [
          1888,
          1856
        ],
        [
          1888,
          1855
        ],
        [
          1889,
          1854
        ],
        [
          1889,
          1850
        ],
        [
          1890,
          1849
        ],
        [
          1890,
          1848
        ],
        [
          1887,
          1845
        ],
        [
          1886,
          1845
        ],
        [
          1886,
          1836
        ],
        [
          1891,
          1834
        ],
        [
          1894,
          1831
        ],
        [
          1899,
          1831
        ],
        [
          1903,
          1827
        ],
        [
          1903,
          1825
        ],
        [
          1904,
          1824
        ],
        [
          1904,
          1809
        ],
        [
          1902,
          1804
        ],
        [
          1902,
          1782
        ],
        [
          1903,
          1781
        ],
        [
          1903,
          1771
        ],
        [
          1904,
          1770
        ],
        [
          1905,
          1764
        ],
        [
          1904,
          1763
        ],
        [
          1904,
          1755
        ],
        [
          1903,
          1754
        ],
        [
          1903,
          1751
        ],
        [
          1906,
          1746
        ],
        [
          1908,
          1739
        ],
        [
          1911,
          1736
        ],
        [
          1913,
          1732
        ],
        [
          1913,
          1727
        ],
        [
          1906,
          1726
        ],
        [
          1903,
          1723
        ],
        [
          1902,
          1719
        ],
        [
          1900,
          1718
        ],
        [
          1900,
          1711
        ],
        [
          1901,
          1711
        ],
        [
          1902,
          1710
        ],
        [
          1910,
          1710
        ],
        [
          1912,
          1708
        ],
        [
          1912,
          1705
        ],
        [
          1913,
          1704
        ],
        [
          1913,
          1696
        ],
        [
          1914,
          1695
        ],
        [
          1914,
          1688
        ],
        [
          1915,
          1687
        ],
        [
          1915,
          1683
        ],
        [
          1913,
          1681
        ],
        [
          1911,
          1681
        ],
        [
          1910,
          1680
        ],
        [
          1905,
          1680
        ],
        [
          1904,
          1679
        ],
        [
          1910,
          1655
        ],
        [
          1913,
          1655
        ],
        [
          1913,
          1652
        ],
        [
          1914,
          1651
        ],
        [
          1914,
          1647
        ],
        [
          1915,
          1646
        ],
        [
          1915,
          1645
        ],
        [
          1916,
          1644
        ],
        [
          1916,
          1643
        ],
        [
          1917,
          1642
        ],
        [
          1917,
          1641
        ],
        [
          1918,
          1640
        ],
        [
          1918,
          1637
        ],
        [
          1917,
          1636
        ],
        [
          1916,
          1636
        ],
        [
          1914,
          1634
        ],
        [
          1913,
          1440
        ],
        [
          1914,
          1439
        ],
        [
          1915,
          1439
        ],
        [
          1917,
          1437
        ],
        [
          1918,
          1437
        ],
        [
          1921,
          1435
        ],
        [
          1921,
          1432
        ],
        [
          1922,
          1431
        ],
        [
          1922,
          1421
        ],
        [
          2190,
          1413
        ],
        [
          2191,
          1414
        ],
        [
          2191,
          1418
        ],
        [
          2192,
          1419
        ],
        [
          2192,
          1424
        ],
        [
          2193,
          1425
        ],
        [
          2193,
          1427
        ],
        [
          2194,
          1427
        ],
        [
          2195,
          1428
        ],
        [
          2202,
          1428
        ],
        [
          2203,
          1429
        ],
        [
          2206,
          1429
        ],
        [
          2218,
          1494
        ],
        [
          2217,
          1495
        ],
        [
          2215,
          1495
        ],
        [
          2214,
          1496
        ],
        [
          2213,
          1496
        ],
        [
          2212,
          1497
        ],
        [
          2211,
          1497
        ],
        [
          2207,
          1501
        ],
        [
          2207,
          1502
        ],
        [
          2206,
          1503
        ],
        [
          2206,
          1505
        ],
        [
          2207,
          1506
        ],
        [
          2207,
          1509
        ],
        [
          2208,
          1510
        ],
        [
          2208,
          1512
        ],
        [
          2209,
          1513
        ],
        [
          2209,
          1515
        ],
        [
          2210,
          1516
        ],
        [
          2210,
          1517
        ],
        [
          2211,
          1518
        ],
        [
          2211,
          1519
        ],
        [
          2212,
          1520
        ],
        [
          2212,
          1521
        ],
        [
          2213,
          1522
        ],
        [
          2213,
          1523
        ],
        [
          2214,
          1524
        ],
        [
          2214,
          1525
        ],
        [
          2217,
          1528
        ],
        [
          2218,
          1528
        ],
        [
          2219,
          1529
        ],
        [
          2220,
          1529
        ],
        [
          2221,
          1530
        ],
        [
          2224,
          1530
        ],
        [
          2225,
          1531
        ],
        [
          2226,
          1531
        ],
        [
          2227,
          1532
        ],
        [
          2228,
          1532
        ],
        [
          2233,
          1537
        ],
        [
          2230,
          1594
        ],
        [
          2233,
          1610
        ],
        [
          2229,
          1622
        ],
        [
          2232,
          1682
        ],
        [
          2218,
          1810
        ],
        [
          2216,
          1924
        ],
        [
          2203,
          1938
        ],
        [
          2202,
          1946
        ],
        [
          2214,
          1984
        ],
        [
          2223,
          2043
        ],
        [
          2221,
          2151
        ],
        [
          2223,
          2159
        ],
        [
          2242,
          2159
        ],
        [
          2247,
          2151
        ],
        [
          2247,
          2118
        ],
        [
          2254,
          2081
        ],
        [
          2262,
          2060
        ],
        [
          2248,
          2026
        ],
        [
          2240,
          1954
        ],
        [
          2250,
          1757
        ],
        [
          2263,
          1687
        ],
        [
          2263,
          1666
        ],
        [
          2254,
          1638
        ],
        [
          2257,
          1624
        ],
        [
          2236,
          1611
        ],
        [
          2239,
          1600
        ],
        [
          2230,
          1594
        ],
        [
          2233,
          1537
        ],
        [
          2233,
          1536
        ],
        [
          2234,
          1535
        ],
        [
          2234,
          1524
        ],
        [
          2233,
          1523
        ],
        [
          2233,
          1517
        ],
        [
          2232,
          1516
        ],
        [
          2232,
          1513
        ],
        [
          2231,
          1512
        ],
        [
          2231,
          1510
        ],
        [
          2230,
          1509
        ],
        [
          2230,
          1506
        ],
        [
          2229,
          1505
        ],
        [
          2229,
          1501
        ],
        [
          2228,
          1500
        ],
        [
          2228,
          1498
        ],
        [
          2226,
          1496
        ],
        [
          2225,
          1496
        ],
        [
          2224,
          1495
        ],
        [
          2222,
          1495
        ],
        [
          2221,
          1494
        ],
        [
          2218,
          1494
        ],
        [
          2206,
          1429
        ],
        [
          2207,
          1428
        ],
        [
          2208,
          1428
        ],
        [
          2208,
          1422
        ],
        [
          2214,
          1416
        ],
        [
          2215,
          1416
        ],
        [
          2217,
          1414
        ],
        [
          2217,
          1412
        ],
        [
          2214,
          1408
        ],
        [
          2214,
          1405
        ],
        [
          2213,
          1404
        ],
        [
          2213,
          1398
        ],
        [
          2214,
          1397
        ],
        [
          2214,
          1394
        ],
        [
          2215,
          1393
        ],
        [
          2215,
          1391
        ],
        [
          2218,
          1386
        ],
        [
          2218,
          1380
        ],
        [
          2217,
          1379
        ],
        [
          2217,
          1372
        ],
        [
          2218,
          1371
        ],
        [
          2218,
          1368
        ],
        [
          2217,
          1367
        ],
        [
          2217,
          1365
        ],
        [
          2216,
          1364
        ],
        [
          2216,
          1361
        ],
        [
          2215,
          1360
        ],
        [
          2215,
          1356
        ],
        [
          2214,
          1355
        ],
        [
          2214,
          1353
        ],
        [
          2213,
          1352
        ],
        [
          2213,
          1351
        ],
        [
          2208,
          1346
        ],
        [
          2208,
          1344
        ],
        [
          2207,
          1343
        ],
        [
          2207,
          1338
        ],
        [
          2206,
          1337
        ],
        [
          2206,
          1336
        ],
        [
          2251,
          1070
        ],
        [
          2276,
          1071
        ],
        [
          2333,
          1079
        ],
        [
          2364,
          1077
        ],
        [
          2394,
          1079
        ],
        [
          2404,
          1076
        ],
        [
          2424,
          1077
        ],
        [
          2432,
          1075
        ],
        [
          2430,
          1069
        ],
        [
          2415,
          1066
        ],
        [
          2404,
          1066
        ],
        [
          2394,
          1071
        ],
        [
          2383,
          1071
        ],
        [
          2355,
          1066
        ],
        [
          2332,
          1067
        ],
        [
          2319,
          1065
        ],
        [
          2283,
          1055
        ],
        [
          2272,
          1045
        ],
        [
          2257,
          1039
        ],
        [
          2245,
          1038
        ],
        [
          2232,
          1045
        ],
        [
          2207,
          1037
        ],
        [
          2178,
          1035
        ],
        [
          2139,
          1017
        ],
        [
          2129,
          1016
        ],
        [
          2126,
          1012
        ],
        [
          2118,
          1015
        ],
        [
          2099,
          1016
        ],
        [
          2096,
          1020
        ],
        [
          2087,
          1020
        ],
        [
          2084,
          1023
        ],
        [
          2020,
          1038
        ],
        [
          2018,
          1036
        ],
        [
          2014,
          1034
        ],
        [
          2012,
          1034
        ],
        [
          2011,
          1033
        ],
        [
          2009,
          1033
        ],
        [
          2005,
          1031
        ],
        [
          2001,
          1031
        ],
        [
          2000,
          1030
        ],
        [
          1992,
          1029
        ],
        [
          1981,
          1023
        ],
        [
          1979,
          1023
        ],
        [
          1973,
          1020
        ],
        [
          1971,
          1018
        ],
        [
          1956,
          1011
        ],
        [
          1954,
          1009
        ],
        [
          1950,
          1007
        ],
        [
          1948,
          1007
        ],
        [
          1940,
          1000
        ],
        [
          1934,
          999
        ],
        [
          1930,
          997
        ],
        [
          1926,
          993
        ],
        [
          1926,
          989
        ],
        [
          1874,
          955
        ],
        [
          1874,
          954
        ],
        [
          1873,
          953
        ],
        [
          1873,
          948
        ],
        [
          1872,
          948
        ],
        [
          1869,
          945
        ],
        [
          1869,
          942
        ],
        [
          1866,
          939
        ],
        [
          1866,
          938
        ],
        [
          1865,
          937
        ],
        [
          1865,
          936
        ],
        [
          1864,
          935
        ],
        [
          1864,
          933
        ],
        [
          1858,
          927
        ],
        [
          1856,
          927
        ],
        [
          1851,
          922
        ],
        [
          1851,
          921
        ],
        [
          1850,
          920
        ],
        [
          1850,
          918
        ],
        [
          1849,
          917
        ],
        [
          1849,
          916
        ],
        [
          1848,
          915
        ],
        [
          1848,
          911
        ],
        [
          1846,
          909
        ],
        [
          2020,
          637
        ],
        [
          2029,
          637
        ],
        [
          2030,
          638
        ],
        [
          2035,
          638
        ],
        [
          2036,
          637
        ],
        [
          2039,
          637
        ],
        [
          2044,
          634
        ],
        [
          2059,
          652
        ],
        [
          2059,
          653
        ],
        [
          2057,
          655
        ],
        [
          2057,
          656
        ],
        [
          2059,
          658
        ],
        [
          2059,
          659
        ],
        [
          2062,
          659
        ],
        [
          2063,
          658
        ],
        [
          2064,
          658
        ],
        [
          2070,
          663
        ],
        [
          2070,
          664
        ],
        [
          2073,
          667
        ],
        [
          2073,
          662
        ],
        [
          2071,
          662
        ],
        [
          2070,
          663
        ],
        [
          2064,
          658
        ],
        [
          2065,
          657
        ],
        [
          2065,
          656
        ],
        [
          2063,
          654
        ],
        [
          2062,
          654
        ],
        [
          2060,
          652
        ],
        [
          2059,
          652
        ],
        [
          2044,
          634
        ],
        [
          2044,
          633
        ],
        [
          2073,
          624
        ],
        [
          2086,
          623
        ],
        [
          2088,
          594
        ],
        [
          2081,
          543
        ],
        [
          2088,
          535
        ],
        [
          2082,
          520
        ],
        [
          2087,
          513
        ],
        [
          2089,
          483
        ],
        [
          2098,
          475
        ],
        [
          2103,
          449
        ],
        [
          2127,
          438
        ],
        [
          2127,
          397
        ],
        [
          2133,
          386
        ],
        [
          2132,
          335
        ],
        [
          2154,
          290
        ],
        [
          2146,
          281
        ],
        [
          2147,
          221
        ],
        [
          2146,
          217
        ],
        [
          2148,
          216
        ],
        [
          2152,
          216
        ],
        [
          2153,
          215
        ],
        [
          2153,
          208
        ],
        [
          2152,
          208
        ],
        [
          2149,
          211
        ],
        [
          2149,
          212
        ],
        [
          2148,
          213
        ],
        [
          2148,
          216
        ],
        [
          2146,
          217
        ],
        [
          2138,
          220
        ],
        [
          2131,
          243
        ],
        [
          2134,
          251
        ],
        [
          2128,
          261
        ],
        [
          2134,
          288
        ],
        [
          2117,
          318
        ],
        [
          2116,
          379
        ],
        [
          2103,
          416
        ],
        [
          2109,
          431
        ],
        [
          2107,
          439
        ],
        [
          2095,
          453
        ],
        [
          2094,
          462
        ],
        [
          2086,
          466
        ],
        [
          2084,
          491
        ],
        [
          2073,
          502
        ],
        [
          2054,
          465
        ],
        [
          2053,
          429
        ],
        [
          2043,
          408
        ],
        [
          2033,
          335
        ],
        [
          2024,
          318
        ],
        [
          2022,
          247
        ],
        [
          2007,
          221
        ],
        [
          2019,
          213
        ],
        [
          2020,
          201
        ],
        [
          2006,
          198
        ],
        [
          2006,
          188
        ],
        [
          2008,
          187
        ],
        [
          2011,
          180
        ],
        [
          2011,
          171
        ],
        [
          2010,
          170
        ],
        [
          2011,
          160
        ],
        [
          2009,
          153
        ],
        [
          2011,
          146
        ],
        [
          2011,
          138
        ],
        [
          2009,
          132
        ],
        [
          2011,
          124
        ],
        [
          2009,
          117
        ],
        [
          2009,
          108
        ],
        [
          2011,
          103
        ],
        [
          2011,
          95
        ],
        [
          2010,
          93
        ],
        [
          2013,
          89
        ],
        [
          2019,
          86
        ],
        [
          2018,
          79
        ],
        [
          2014,
          74
        ],
        [
          2012,
          63
        ],
        [
          2008,
          56
        ],
        [
          2006,
          32
        ],
        [
          2007,
          29
        ],
        [
          2010,
          26
        ],
        [
          2019,
          24
        ],
        [
          2020,
          17
        ],
        [
          2013,
          18
        ],
        [
          2012,
          22
        ],
        [
          2010,
          24
        ],
        [
          2006,
          25
        ],
        [
          2006,
          35
        ],
        [
          2004,
          41
        ],
        [
          2005,
          48
        ],
        [
          1997,
          63
        ],
        [
          1968,
          63
        ],
        [
          1966,
          61
        ],
        [
          1966,
          60
        ],
        [
          1965,
          61
        ],
        [
          1963,
          61
        ],
        [
          1962,
          62
        ],
        [
          1961,
          62
        ],
        [
          1960,
          63
        ],
        [
          1960,
          64
        ],
        [
          1962,
          66
        ],
        [
          1962,
          67
        ],
        [
          1965,
          70
        ],
        [
          1965,
          71
        ],
        [
          1964,
          72
        ],
        [
          1964,
          73
        ],
        [
          1963,
          74
        ],
        [
          1963,
          77
        ],
        [
          1962,
          78
        ],
        [
          1963,
          79
        ],
        [
          1963,
          80
        ],
        [
          1964,
          81
        ],
        [
          1964,
          82
        ],
        [
          1965,
          83
        ],
        [
          1965,
          84
        ],
        [
          1966,
          85
        ],
        [
          1966,
          88
        ],
        [
          1965,
          89
        ],
        [
          1965,
          91
        ],
        [
          1964,
          92
        ],
        [
          1964,
          93
        ],
        [
          1965,
          94
        ],
        [
          1965,
          95
        ],
        [
          1966,
          96
        ],
        [
          1966,
          105
        ],
        [
          1966,
          106
        ],
        [
          1965,
          107
        ],
        [
          1965,
          110
        ],
        [
          1966,
          111
        ],
        [
          1966,
          112
        ],
        [
          1969,
          109
        ],
        [
          1969,
          108
        ],
        [
          1966,
          105
        ],
        [
          1966,
          96
        ],
        [
          1967,
          95
        ],
        [
          1967,
          94
        ],
        [
          1968,
          93
        ],
        [
          1968,
          92
        ],
        [
          1967,
          91
        ],
        [
          1967,
          88
        ],
        [
          1966,
          87
        ],
        [
          1966,
          84
        ],
        [
          1967,
          83
        ],
        [
          1967,
          81
        ],
        [
          1968,
          80
        ],
        [
          1968,
          76
        ],
        [
          1967,
          75
        ],
        [
          1967,
          72
        ],
        [
          1966,
          71
        ],
        [
          1966,
          70
        ],
        [
          1967,
          69
        ],
        [
          1967,
          66
        ],
        [
          1968,
          65
        ],
        [
          1968,
          63
        ],
        [
          1997,
          63
        ],
        [
          1999,
          72
        ],
        [
          1999,
          80
        ],
        [
          2004,
          90
        ],
        [
          2003,
          117
        ],
        [
          2000,
          125
        ],
        [
          2003,
          131
        ],
        [
          2002,
          147
        ],
        [
          2003,
          148
        ],
        [
          2004,
          171
        ],
        [
          2003,
          172
        ],
        [
          2003,
          182
        ],
        [
          2002,
          183
        ],
        [
          2006,
          188
        ],
        [
          2006,
          198
        ],
        [
          1986,
          218
        ],
        [
          1975,
          215
        ],
        [
          1973,
          212
        ],
        [
          1980,
          198
        ],
        [
          1981,
          197
        ],
        [
          1981,
          196
        ],
        [
          1982,
          195
        ],
        [
          1982,
          192
        ],
        [
          1983,
          191
        ],
        [
          1983,
          190
        ],
        [
          1982,
          189
        ],
        [
          1982,
          183
        ],
        [
          1981,
          183
        ],
        [
          1980,
          182
        ],
        [
          1979,
          183
        ],
        [
          1979,
          196
        ],
        [
          1980,
          197
        ],
        [
          1980,
          198
        ],
        [
          1973,
          212
        ],
        [
          1967,
          211
        ],
        [
          1962,
          209
        ],
        [
          1959,
          205
        ],
        [
          1949,
          201
        ],
        [
          1940,
          194
        ],
        [
          1937,
          194
        ],
        [
          1926,
          183
        ],
        [
          1920,
          180
        ],
        [
          1914,
          175
        ],
        [
          1907,
          172
        ],
        [
          1903,
          168
        ],
        [
          1899,
          166
        ],
        [
          1894,
          165
        ],
        [
          1891,
          162
        ],
        [
          1887,
          153
        ],
        [
          1872,
          153
        ],
        [
          1865,
          146
        ],
        [
          1865,
          141
        ],
        [
          1866,
          140
        ],
        [
          1866,
          138
        ],
        [
          1864,
          136
        ],
        [
          1864,
          135
        ],
        [
          1862,
          133
        ],
        [
          1862,
          132
        ],
        [
          1860,
          130
        ],
        [
          1855,
          130
        ],
        [
          1854,
          131
        ],
        [
          1848,
          131
        ],
        [
          1847,
          132
        ],
        [
          1845,
          132
        ],
        [
          1844,
          131
        ],
        [
          1841,
          131
        ],
        [
          1840,
          130
        ],
        [
          1838,
          130
        ],
        [
          1837,
          129
        ],
        [
          1836,
          129
        ],
        [
          1835,
          128
        ],
        [
          1834,
          128
        ],
        [
          1833,
          127
        ],
        [
          1829,
          127
        ],
        [
          1825,
          124
        ],
        [
          1823,
          119
        ],
        [
          1823,
          116
        ],
        [
          1820,
          114
        ],
        [
          1817,
          114
        ],
        [
          1806,
          110
        ],
        [
          1801,
          110
        ],
        [
          1800,
          109
        ],
        [
          1796,
          109
        ],
        [
          1795,
          108
        ],
        [
          1791,
          108
        ],
        [
          1785,
          106
        ],
        [
          1775,
          101
        ],
        [
          1766,
          98
        ],
        [
          1763,
          98
        ],
        [
          1759,
          96
        ],
        [
          1758,
          94
        ],
        [
          1755,
          92
        ],
        [
          1752,
          92
        ],
        [
          1751,
          91
        ],
        [
          1736,
          91
        ],
        [
          1735,
          90
        ],
        [
          1717,
          90
        ],
        [
          1714,
          89
        ],
        [
          1711,
          86
        ],
        [
          1705,
          85
        ],
        [
          1704,
          84
        ],
        [
          1686,
          84
        ],
        [
          1685,
          85
        ],
        [
          1679,
          86
        ],
        [
          1698,
          94
        ],
        [
          1714,
          94
        ],
        [
          1715,
          95
        ],
        [
          1721,
          95
        ],
        [
          1722,
          96
        ],
        [
          1731,
          96
        ],
        [
          1732,
          97
        ],
        [
          1737,
          97
        ],
        [
          1738,
          98
        ],
        [
          1746,
          99
        ],
        [
          1750,
          101
        ],
        [
          1761,
          102
        ],
        [
          1767,
          105
        ],
        [
          1770,
          108
        ],
        [
          1780,
          110
        ],
        [
          1781,
          111
        ],
        [
          1786,
          111
        ],
        [
          1788,
          112
        ],
        [
          1791,
          116
        ],
        [
          1800,
          117
        ],
        [
          1806,
          121
        ],
        [
          1816,
          123
        ],
        [
          1819,
          125
        ],
        [
          1824,
          125
        ],
        [
          1825,
          124
        ],
        [
          1829,
          127
        ],
        [
          1828,
          128
        ],
        [
          1828,
          129
        ],
        [
          1827,
          130
        ],
        [
          1828,
          131
        ],
        [
          1830,
          131
        ],
        [
          1833,
          134
        ],
        [
          1836,
          134
        ],
        [
          1837,
          135
        ],
        [
          1838,
          135
        ],
        [
          1840,
          137
        ],
        [
          1840,
          138
        ],
        [
          1841,
          139
        ],
        [
          1841,
          142
        ],
        [
          1842,
          143
        ],
        [
          1842,
          146
        ],
        [
          1843,
          147
        ],
        [
          1843,
          148
        ],
        [
          1845,
          150
        ],
        [
          1848,
          150
        ],
        [
          1849,
          149
        ],
        [
          1852,
          149
        ],
        [
          1853,
          148
        ],
        [
          1857,
          148
        ],
        [
          1858,
          147
        ],
        [
          1862,
          147
        ],
        [
          1863,
          146
        ],
        [
          1865,
          146
        ],
        [
          1872,
          153
        ],
        [
          1875,
          160
        ],
        [
          1882,
          163
        ],
        [
          1886,
          168
        ],
        [
          1893,
          170
        ],
        [
          1896,
          176
        ],
        [
          1899,
          178
        ],
        [
          1904,
          179
        ],
        [
          1914,
          190
        ],
        [
          1930,
          197
        ],
        [
          1933,
          199
        ],
        [
          1939,
          206
        ],
        [
          1946,
          208
        ],
        [
          1949,
          210
        ],
        [
          1953,
          215
        ],
        [
          1957,
          216
        ],
        [
          1962,
          221
        ],
        [
          1962,
          232
        ],
        [
          1961,
          233
        ],
        [
          1961,
          235
        ],
        [
          1968,
          235
        ],
        [
          1975,
          228
        ],
        [
          1975,
          215
        ],
        [
          1986,
          218
        ],
        [
          1986,
          235
        ],
        [
          2002,
          277
        ],
        [
          2003,
          304
        ],
        [
          2010,
          318
        ],
        [
          2013,
          357
        ],
        [
          2027,
          407
        ],
        [
          2031,
          446
        ],
        [
          2038,
          455
        ],
        [
          2045,
          507
        ],
        [
          2053,
          526
        ],
        [
          2052,
          539
        ],
        [
          2063,
          580
        ],
        [
          2060,
          589
        ],
        [
          2073,
          610
        ],
        [
          2073,
          624
        ],
        [
          2044,
          633
        ],
        [
          2043,
          633
        ],
        [
          2042,
          632
        ],
        [
          2039,
          631
        ],
        [
          2037,
          629
        ],
        [
          2034,
          628
        ],
        [
          2032,
          626
        ],
        [
          2032,
          624
        ],
        [
          2033,
          623
        ],
        [
          2033,
          615
        ],
        [
          2032,
          614
        ],
        [
          2032,
          611
        ],
        [
          2031,
          610
        ],
        [
          2031,
          607
        ],
        [
          2030,
          606
        ],
        [
          2030,
          604
        ],
        [
          2027,
          601
        ],
        [
          2026,
          601
        ],
        [
          2021,
          597
        ],
        [
          2020,
          597
        ],
        [
          2019,
          596
        ],
        [
          2018,
          596
        ],
        [
          2017,
          595
        ],
        [
          2016,
          595
        ],
        [
          2011,
          592
        ],
        [
          2009,
          592
        ],
        [
          2006,
          590
        ],
        [
          2001,
          590
        ],
        [
          2000,
          589
        ],
        [
          1999,
          589
        ],
        [
          1994,
          586
        ],
        [
          1993,
          586
        ],
        [
          1990,
          574
        ],
        [
          1990,
          573
        ],
        [
          1987,
          573
        ],
        [
          1986,
          572
        ],
        [
          1983,
          572
        ],
        [
          1982,
          571
        ],
        [
          1981,
          571
        ],
        [
          1980,
          570
        ],
        [
          1979,
          571
        ],
        [
          1979,
          577
        ],
        [
          1980,
          578
        ],
        [
          1980,
          580
        ],
        [
          1984,
          576
        ],
        [
          1985,
          576
        ],
        [
          1986,
          575
        ],
        [
          1987,
          575
        ],
        [
          1988,
          574
        ],
        [
          1990,
          574
        ],
        [
          1993,
          586
        ],
        [
          1991,
          588
        ],
        [
          1991,
          589
        ],
        [
          1993,
          592
        ],
        [
          1993,
          594
        ],
        [
          1996,
          597
        ],
        [
          1997,
          597
        ],
        [
          2003,
          603
        ],
        [
          2003,
          619
        ],
        [
          2005,
          621
        ],
        [
          2006,
          621
        ],
        [
          2011,
          626
        ],
        [
          2012,
          626
        ],
        [
          2019,
          633
        ],
        [
          2019,
          635
        ],
        [
          2020,
          636
        ],
        [
          2020,
          637
        ],
        [
          1846,
          909
        ],
        [
          1842,
          909
        ],
        [
          1841,
          910
        ],
        [
          1840,
          910
        ],
        [
          1840,
          913
        ],
        [
          1841,
          914
        ],
        [
          1841,
          916
        ],
        [
          1842,
          917
        ],
        [
          1842,
          920
        ],
        [
          1841,
          921
        ],
        [
          1841,
          925
        ],
        [
          1840,
          926
        ],
        [
          1840,
          931
        ],
        [
          1839,
          932
        ],
        [
          1839,
          933
        ],
        [
          1840,
          934
        ],
        [
          1841,
          934
        ],
        [
          1843,
          936
        ],
        [
          1844,
          936
        ],
        [
          1845,
          937
        ],
        [
          1846,
          937
        ],
        [
          1849,
          940
        ],
        [
          1849,
          941
        ],
        [
          1850,
          941
        ],
        [
          1852,
          943
        ],
        [
          1853,
          943
        ],
        [
          1857,
          947
        ],
        [
          1858,
          947
        ],
        [
          1859,
          948
        ],
        [
          1865,
          948
        ],
        [
          1866,
          949
        ],
        [
          1869,
          949
        ],
        [
          1872,
          952
        ],
        [
          1872,
          955
        ],
        [
          1873,
          956
        ],
        [
          1874,
          955
        ],
        [
          1926,
          989
        ],
        [
          1926,
          995
        ],
        [
          1924,
          999
        ],
        [
          1925,
          1007
        ],
        [
          1932,
          1014
        ],
        [
          1934,
          1018
        ],
        [
          1937,
          1021
        ],
        [
          1940,
          1022
        ],
        [
          1943,
          1025
        ],
        [
          1953,
          1030
        ],
        [
          1955,
          1032
        ],
        [
          1963,
          1036
        ],
        [
          1968,
          1037
        ],
        [
          1973,
          1040
        ],
        [
          1981,
          1041
        ],
        [
          1989,
          1045
        ],
        [
          1991,
          1047
        ],
        [
          1996,
          1047
        ],
        [
          1997,
          1048
        ],
        [
          2007,
          1048
        ],
        [
          2011,
          1046
        ],
        [
          2014,
          1046
        ],
        [
          2020,
          1039
        ],
        [
          2020,
          1038
        ],
        [
          2084,
          1023
        ],
        [
          2086,
          1025
        ],
        [
          2098,
          1024
        ],
        [
          2105,
          1019
        ],
        [
          2113,
          1018
        ],
        [
          2127,
          1031
        ],
        [
          2131,
          1039
        ],
        [
          2141,
          1045
        ],
        [
          2169,
          1050
        ],
        [
          2179,
          1054
        ],
        [
          2222,
          1050
        ],
        [
          2242,
          1067
        ],
        [
          2251,
          1070
        ],
        [
          2206,
          1336
        ],
        [
          2203,
          1339
        ],
        [
          2203,
          1346
        ],
        [
          2201,
          1348
        ],
        [
          2201,
          1349
        ],
        [
          2199,
          1352
        ],
        [
          2199,
          1356
        ],
        [
          2198,
          1357
        ],
        [
          2198,
          1365
        ],
        [
          2199,
          1366
        ],
        [
          2199,
          1371
        ],
        [
          2200,
          1372
        ],
        [
          2200,
          1377
        ],
        [
          2194,
          1385
        ],
        [
          2194,
          1388
        ],
        [
          2193,
          1389
        ],
        [
          2193,
          1399
        ],
        [
          2192,
          1400
        ],
        [
          2192,
          1402
        ],
        [
          2190,
          1405
        ],
        [
          2190,
          1413
        ],
        [
          1922,
          1421
        ],
        [
          1921,
          1420
        ],
        [
          1921,
          1401
        ],
        [
          1920,
          1400
        ],
        [
          1920,
          1389
        ],
        [
          1919,
          1388
        ],
        [
          1919,
          1386
        ],
        [
          1918,
          1385
        ],
        [
          1918,
          1376
        ],
        [
          1917,
          1375
        ],
        [
          1917,
          1368
        ],
        [
          1913,
          1363
        ],
        [
          1910,
          1363
        ],
        [
          1909,
          1364
        ],
        [
          1908,
          1364
        ],
        [
          1906,
          1366
        ],
        [
          1813,
          1316
        ],
        [
          1809,
          1312
        ],
        [
          1804,
          1311
        ],
        [
          1792,
          1314
        ],
        [
          1776,
          1316
        ],
        [
          1766,
          1323
        ],
        [
          1740,
          1320
        ],
        [
          1728,
          1316
        ],
        [
          1724,
          1311
        ],
        [
          1712,
          1310
        ],
        [
          1706,
          1306
        ],
        [
          1693,
          1304
        ],
        [
          1688,
          1298
        ],
        [
          1683,
          1296
        ],
        [
          1679,
          1286
        ],
        [
          1675,
          1285
        ],
        [
          1673,
          1283
        ],
        [
          1670,
          1283
        ],
        [
          1662,
          1278
        ],
        [
          1657,
          1278
        ],
        [
          1654,
          1287
        ],
        [
          1649,
          1292
        ],
        [
          1646,
          1293
        ],
        [
          1611,
          1256
        ],
        [
          1569,
          1213
        ],
        [
          1566,
          1187
        ],
        [
          1553,
          1188
        ],
        [
          1515,
          1151
        ],
        [
          1518,
          1143
        ],
        [
          1465,
          1068
        ],
        [
          1438,
          1048
        ],
        [
          1334,
          865
        ],
        [
          1331,
          843
        ],
        [
          1304,
          820
        ],
        [
          1299,
          803
        ],
        [
          1288,
          792
        ],
        [
          1288,
          788
        ],
        [
          1287,
          787
        ],
        [
          1287,
          785
        ],
        [
          1286,
          784
        ],
        [
          1286,
          783
        ],
        [
          1275,
          776
        ],
        [
          1275,
          774
        ],
        [
          1274,
          773
        ],
        [
          1274,
          770
        ],
        [
          1273,
          769
        ],
        [
          1273,
          767
        ],
        [
          1272,
          768
        ],
        [
          1272,
          774
        ],
        [
          1271,
          775
        ],
        [
          1273,
          777
        ],
        [
          1274,
          776
        ],
        [
          1275,
          776
        ],
        [
          1286,
          783
        ],
        [
          1286,
          785
        ],
        [
          1285,
          786
        ],
        [
          1285,
          791
        ],
        [
          1286,
          792
        ],
        [
          1286,
          793
        ],
        [
          1287,
          793
        ],
        [
          1288,
          792
        ],
        [
          1299,
          803
        ],
        [
          1285,
          813
        ],
        [
          1205,
          746
        ],
        [
          1137,
          708
        ],
        [
          1006,
          654
        ]
      ],
      "group_id": null,
      "description": "",
      "shape_type": "polygon",
      "flags": {}
    },
    {
      "label": "flower",
      "points": [
        [
          1468,
          850
        ],
        [
          1467,
          851
        ],
        [
          1465,
          851
        ],
        [
          1464,
          852
        ],
        [
          1462,
          852
        ],
        [
          1461,
          853
        ],
        [
          1460,
          853
        ],
        [
          1456,
          858
        ],
        [
          1456,
          860
        ],
        [
          1455,
          861
        ],
        [
          1455,
          863
        ],
        [
          1454,
          864
        ],
        [
          1454,
          866
        ],
        [
          1453,
          867
        ],
        [
          1453,
          871
        ],
        [
          1452,
          872
        ],
        [
          1452,
          882
        ],
        [
          1453,
          883
        ],
        [
          1454,
          888
        ],
        [
          1455,
          889
        ],
        [
          1457,
          894
        ],
        [
          1459,
          896
        ],
        [
          1459,
          897
        ],
        [
          1467,
          905
        ],
        [
          1468,
          905
        ],
        [
          1471,
          908
        ],
        [
          1472,
          908
        ],
        [
          1473,
          909
        ],
        [
          1476,
          909
        ],
        [
          1477,
          908
        ],
        [
          1484,
          908
        ],
        [
          1485,
          907
        ],
        [
          1486,
          907
        ],
        [
          1491,
          902
        ],
        [
          1491,
          901
        ],
        [
          1494,
          896
        ],
        [
          1494,
          893
        ],
        [
          1495,
          892
        ],
        [
          1496,
          887
        ],
        [
          1503,
          880
        ],
        [
          1504,
          880
        ],
        [
          1507,
          878
        ],
        [
          1509,
          878
        ],
        [
          1510,
          877
        ],
        [
          1513,
          877
        ],
        [
          1514,
          876
        ],
        [
          1517,
          875
        ],
        [
          1518,
          874
        ],
        [
          1518,
          873
        ],
        [
          1516,
          871
        ],
        [
          1515,
          871
        ],
        [
          1513,
          869
        ],
        [
          1508,
          867
        ],
        [
          1504,
          863
        ],
        [
          1503,
          863
        ],
        [
          1501,
          861
        ],
        [
          1501,
          860
        ],
        [
          1497,
          856
        ],
        [
          1495,
          856
        ],
        [
          1494,
          855
        ],
        [
          1491,
          855
        ],
        [
          1490,
          854
        ],
        [
          1486,
          854
        ],
        [
          1485,
          853
        ],
        [
          1482,
          853
        ],
        [
          1481,
          852
        ],
        [
          1479,
          852
        ],
        [
          1476,
          850
        ]
      ],
      "group_id": null,
      "description": "",
      "shape_type": "polygon",
      "flags": {}
    },
    {
      "label": "flower",
      "points": [
        [
          1555,
          821
        ],
        [
          1551,
          825
        ],
        [
          1551,
          826
        ],
        [
          1548,
          829
        ],
        [
          1548,
          830
        ],
        [
          1545,
          835
        ],
        [
          1545,
          841
        ],
        [
          1544,
          842
        ],
        [
          1544,
          843
        ],
        [
          1548,
          847
        ],
        [
          1548,
          848
        ],
        [
          1551,
          851
        ],
        [
          1552,
          851
        ],
        [
          1553,
          852
        ],
        [
          1554,
          852
        ],
        [
          1555,
          853
        ],
        [
          1558,
          854
        ],
        [
          1560,
          856
        ],
        [
          1561,
          856
        ],
        [
          1562,
          857
        ],
        [
          1563,
          857
        ],
        [
          1564,
          858
        ],
        [
          1565,
          858
        ],
        [
          1566,
          859
        ],
        [
          1569,
          860
        ],
        [
          1571,
          862
        ],
        [
          1572,
          862
        ],
        [
          1580,
          870
        ],
        [
          1581,
          869
        ],
        [
          1584,
          869
        ],
        [
          1585,
          868
        ],
        [
          1587,
          868
        ],
        [
          1588,
          867
        ],
        [
          1591,
          866
        ],
        [
          1593,
          863
        ],
        [
          1593,
          857
        ],
        [
          1594,
          856
        ],
        [
          1594,
          851
        ],
        [
          1595,
          850
        ],
        [
          1595,
          847
        ],
        [
          1596,
          846
        ],
        [
          1596,
          834
        ],
        [
          1595,
          833
        ],
        [
          1595,
          829
        ],
        [
          1594,
          828
        ],
        [
          1593,
          825
        ],
        [
          1587,
          819
        ],
        [
          1586,
          819
        ],
        [
          1583,
          817
        ],
        [
          1581,
          817
        ],
        [
          1580,
          816
        ],
        [
          1566,
          816
        ],
        [
          1563,
          818
        ],
        [
          1561,
          818
        ],
        [
          1560,
          819
        ],
        [
          1559,
          819
        ],
        [
          1558,
          820
        ]
      ],
      "group_id": null,
      "description": "",
      "shape_type": "polygon",
      "flags": {}
    },
    {
      "label": "flower",
      "points": [
        [
          1472,
          806
        ],
        [
          1471,
          807
        ],
        [
          1471,
          808
        ],
        [
          1470,
          809
        ],
        [
          1470,
          810
        ],
        [
          1469,
          811
        ],
        [
          1469,
          812
        ],
        [
          1467,
          814
        ],
        [
          1467,
          815
        ],
        [
          1464,
          818
        ],
        [
          1464,
          819
        ],
        [
          1462,
          821
        ],
        [
          1462,
          822
        ],
        [
          1461,
          823
        ],
        [
          1461,
          824
        ],
        [
          1460,
          825
        ],
        [
          1460,
          826
        ],
        [
          1459,
          827
        ],
        [
          1459,
          831
        ],
        [
          1460,
          832
        ],
        [
          1460,
          834
        ],
        [
          1462,
          836
        ],
        [
          1464,
          836
        ],
        [
          1465,
          837
        ],
        [
          1467,
          837
        ],
        [
          1468,
          838
        ],
        [
          1471,
          838
        ],
        [
          1472,
          839
        ],
        [
          1476,
          839
        ],
        [
          1477,
          840
        ],
        [
          1480,
          840
        ],
        [
          1481,
          841
        ],
        [
          1483,
          841
        ],
        [
          1484,
          842
        ],
        [
          1485,
          842
        ],
        [
          1486,
          843
        ],
        [
          1487,
          842
        ],
        [
          1489,
          842
        ],
        [
          1490,
          841
        ],
        [
          1491,
          841
        ],
        [
          1493,
          839
        ],
        [
          1494,
          839
        ],
        [
          1498,
          835
        ],
        [
          1498,
          828
        ],
        [
          1495,
          825
        ],
        [
          1495,
          824
        ],
        [
          1487,
          816
        ],
        [
          1487,
          815
        ],
        [
          1485,
          813
        ],
        [
          1484,
          813
        ],
        [
          1483,
          812
        ],
        [
          1482,
          812
        ],
        [
          1481,
          811
        ],
        [
          1480,
          811
        ],
        [
          1475,
          806
        ]
      ],
      "group_id": null,
      "description": "",
      "shape_type": "polygon",
      "flags": {}
    },
    {
      "label": "flower",
      "points": [
        [
          1593,
          758
        ],
        [
          1590,
          761
        ],
        [
          1590,
          762
        ],
        [
          1587,
          765
        ],
        [
          1587,
          766
        ],
        [
          1582,
          771
        ],
        [
          1581,
          771
        ],
        [
          1578,
          773
        ],
        [
          1576,
          773
        ],
        [
          1575,
          774
        ],
        [
          1572,
          774
        ],
        [
          1571,
          775
        ],
        [
          1565,
          775
        ],
        [
          1564,
          776
        ],
        [
          1553,
          776
        ],
        [
          1552,
          777
        ],
        [
          1549,
          778
        ],
        [
          1547,
          780
        ],
        [
          1547,
          781
        ],
        [
          1545,
          783
        ],
        [
          1545,
          784
        ],
        [
          1546,
          785
        ],
        [
          1546,
          792
        ],
        [
          1547,
          793
        ],
        [
          1547,
          795
        ],
        [
          1549,
          798
        ],
        [
          1549,
          801
        ],
        [
          1550,
          802
        ],
        [
          1550,
          804
        ],
        [
          1551,
          805
        ],
        [
          1551,
          806
        ],
        [
          1554,
          809
        ],
        [
          1555,
          809
        ],
        [
          1560,
          812
        ],
        [
          1562,
          812
        ],
        [
          1563,
          813
        ],
        [
          1569,
          813
        ],
        [
          1570,
          812
        ],
        [
          1572,
          812
        ],
        [
          1573,
          811
        ],
        [
          1576,
          811
        ],
        [
          1577,
          810
        ],
        [
          1579,
          810
        ],
        [
          1580,
          809
        ],
        [
          1582,
          809
        ],
        [
          1583,
          808
        ],
        [
          1585,
          808
        ],
        [
          1586,
          807
        ],
        [
          1588,
          807
        ],
        [
          1589,
          806
        ],
        [
          1591,
          806
        ],
        [
          1592,
          805
        ],
        [
          1593,
          805
        ],
        [
          1600,
          799
        ],
        [
          1601,
          799
        ],
        [
          1602,
          798
        ],
        [
          1603,
          798
        ],
        [
          1605,
          796
        ],
        [
          1606,
          796
        ],
        [
          1611,
          791
        ],
        [
          1610,
          786
        ],
        [
          1600,
          777
        ],
        [
          1600,
          776
        ],
        [
          1599,
          775
        ],
        [
          1599,
          773
        ],
        [
          1598,
          772
        ],
        [
          1598,
          769
        ],
        [
          1597,
          768
        ],
        [
          1596,
          763
        ]
      ],
      "group_id": null,
      "description": "",
      "shape_type": "polygon",
      "flags": {}
    }
  ],
  "imagePath": "20260429_153259_frame_00050.jpg",
  "imageData": null,
  "imageHeight": 2160,
  "imageWidth": 3840
}